{
  "onegai-cinderella": {
    "title": "お願い！シンデレラ",
    "type": "song",
    "orderInType": 0,
    "version": 202303110300
  },
  "star": {
    "title": "Star!!",
    "type": "song",
    "orderInType": 81,
    "version": 202303110300
  },
  "smileing": {
    "title": "S(mile)ING!",
    "type": "song",
    "orderInType": 1,
    "version": 202303110300
  },
  "never-say-never": {
    "title": "Never say never",
    "type": "song",
    "orderInType": 2,
    "version": 202303110300
  },
  "mitsuboshi": {
    "title": "ミツボシ☆☆★",
    "type": "song",
    "orderInType": 3,
    "version": 202303110300
  },
  "onedari-shall-we": {
    "title": "おねだり Shall we 〜？",
    "type": "song",
    "orderInType": 4,
    "version": 202303110300
  },
  "twilight-sky": {
    "title": "Twilight Sky",
    "type": "song",
    "orderInType": 5,
    "version": 202303110300
  },
  "dokidoki-rhythm": {
    "title": "DOKIDOKIリズム",
    "type": "song",
    "orderInType": 6,
    "version": 202303160100
  },
  "kazeiro-melody": {
    "title": "風色メロディ",
    "type": "song",
    "orderInType": 7,
    "version": 202303160100
  },
  "marshmallow-kiss": {
    "title": "ましゅまろ☆キッス",
    "type": "song",
    "orderInType": 8,
    "version": 202303160100
  },
  "anzu-no-uta": {
    "title": "あんずのうた",
    "type": "song",
    "orderInType": 9,
    "version": 202303160100
  },
  "tsubomi": {
    "title": "華蕾夢ミル狂詩曲～魂ノ導～",
    "type": "song",
    "orderInType": 10,
    "version": 202303160000
  },
  "chocolate-tiara": {
    "title": "ショコラ・ティアラ",
    "type": "song",
    "orderInType": 11,
    "version": 202303160000
  },
  "venus-syndrome": {
    "title": "ヴィーナスシンドローム",
    "type": "song",
    "orderInType": 12,
    "version": 202303160000
  },
  "romantic-now": {
    "title": "Romantic Now",
    "type": "song",
    "orderInType": 13,
    "version": 202303160000
  },
  "you-re-stars-shine-on-me": {
    "title": "You’re stars shine on me",
    "type": "song",
    "orderInType": 14,
    "version": 202303160000
  },
  "tokimeki-escalate": {
    "title": "TOKIMEKIエスカレート",
    "type": "song",
    "orderInType": 15,
    "version": 202303160000
  },
  "naked-romance": {
    "title": "Naked Romance",
    "type": "song",
    "orderInType": 16,
    "version": 202303160000
  },
  "angel-breeze": {
    "title": "Angel Breeze",
    "type": "song",
    "orderInType": 17,
    "version": 202303160000
  },
  "apple-pie-princess": {
    "title": "アップルパイ・プリンセス",
    "type": "song",
    "orderInType": 18,
    "version": 202303160000
  },
  "everyday-dream": {
    "title": "エヴリデイドリーム",
    "type": "song",
    "orderInType": 19,
    "version": 202303160000
  },
  "bright-blue": {
    "title": "Bright Blue",
    "type": "song",
    "orderInType": 20,
    "version": 202303160000
  },
  "rockin-emotion": {
    "title": "Rockin’ Emotion",
    "type": "song",
    "orderInType": 21,
    "version": 202303210000
  },
  "hanakanzashi": {
    "title": "花簪 HANAKANZASHI",
    "type": "song",
    "orderInType": 22,
    "version": 202303210000
  },
  "hotel-moonside": {
    "title": "Hotel Moonside",
    "type": "song",
    "orderInType": 23,
    "version": 202303210000
  },
  "osanpo-camera": {
    "title": "お散歩カメラ",
    "type": "song",
    "orderInType": 24,
    "version": 202303210000
  },
  "marchen-debut": {
    "title": "メルヘンデビュー!",
    "type": "song",
    "orderInType": 25,
    "version": 202303210000
  },
  "2nd-side": {
    "title": "2nd SIDE",
    "type": "song",
    "orderInType": 26,
    "version": 202303210000
  },
  "nekketsu-otome-a": {
    "title": "熱血乙女A",
    "type": "song",
    "orderInType": 27,
    "version": 202303210000
  },
  "kimagure-cafe-au-lait": {
    "title": "き・ま・ぐ・れ☆Cafe au lait !",
    "type": "song",
    "orderInType": 28,
    "version": 202303210000
  },
  "hakka": {
    "title": "薄荷 -ハッカ-",
    "type": "song",
    "orderInType": 29,
    "version": 202303210000
  }
}
